builddevenv/Builder.py
builddevenv/__init__.py
builddevenv/__main__.py
test/__init__.py
test/test_builddevenv.py
builddevenv-1.0.dist-info/LICENSE
builddevenv-1.0.dist-info/METADATA
builddevenv-1.0.dist-info/WHEEL
builddevenv-1.0.dist-info/entry_points.txt
builddevenv-1.0.dist-info/top_level.txt
builddevenv-1.0.dist-info/RECORD
