Metadata-Version: 2.1
Name: builddevenv
Version: 1.0
Summary: Module that makes, in a development context, the creation of dockers containers easier.
Home-page: https://github.com/djadeau-dvc/BuildDevEnv
Author: Damien JADEAU
License: GPL V3
Keywords: docker development deploy
Platform: UNKNOWN
Classifier: Topic :: Education
Classifier: Topic :: Documentation
Classifier: Development Status :: 5 - Production/Stable
Classifier: Intended Audience :: Developers
Classifier: Topic :: Software Development :: Build Tools
Requires-Python: >=3.6
Requires-Dist: docker (==4.4.1)
Requires-Dist: PyYAML (==5.4.1)
